Metadata-Version: 2.1
Name: tstools-Kingsley
Version: 0.1
Summary: A package to analyse timeseries
Author-email: Kingsley Oguma <kemukperuo@email.com>
License: MIT
Project-URL: Source, https://example.com
Requires-Dist: numpy
Requires-Dist: matplotlib
Requires-Dist: scipy
